wfuzz/__init__.py
wfuzz/__main__.py
wfuzz/advanced.rst
wfuzz/api.py
wfuzz/core.py
wfuzz/dictionaries.py
wfuzz/exception.py
wfuzz/facade.py
wfuzz/fuzzobjects.py
wfuzz/fuzzqueues.py
wfuzz/fuzzrequest.py
wfuzz/mixins.py
wfuzz/myhttp.py
wfuzz/myqueues.py
wfuzz/options.py
wfuzz/wfuzz.py
wfuzz/externals/__init__.py
wfuzz/externals/moduleman/__init__.py
wfuzz/externals/moduleman/loader.py
wfuzz/externals/moduleman/modulefilter.py
wfuzz/externals/moduleman/plugin.py
wfuzz/externals/moduleman/registrant.py
wfuzz/externals/reqresp/Request.py
wfuzz/externals/reqresp/Response.py
wfuzz/externals/reqresp/TextParser.py
wfuzz/externals/reqresp/Variables.py
wfuzz/externals/reqresp/__init__.py
wfuzz/externals/reqresp/cache.py
wfuzz/externals/reqresp/exceptions.py
wfuzz/externals/settings/__init__.py
wfuzz/externals/settings/settings.py
wfuzz/factories/__init__.py
wfuzz/factories/dictfactory.py
wfuzz/factories/fuzzfactory.py
wfuzz/factories/fuzzresfactory.py
wfuzz/factories/payman.py
wfuzz/factories/plugin_factory.py
wfuzz/factories/reqresp_factory.py
wfuzz/filters/__init__.py
wfuzz/filters/ppfilter.py
wfuzz/filters/simplefilter.py
wfuzz/helpers/__init__.py
wfuzz/helpers/file_func.py
wfuzz/helpers/obj_dic.py
wfuzz/helpers/obj_dyn.py
wfuzz/helpers/obj_factory.py
wfuzz/helpers/str_func.py
wfuzz/helpers/utils.py
wfuzz/plugin_api/__init__.py
wfuzz/plugin_api/base.py
wfuzz/plugin_api/mixins.py
wfuzz/plugin_api/payloadtools.py
wfuzz/plugin_api/urlutils.py
wfuzz/plugins/__init__.py
wfuzz/plugins/encoders/__init__.py
wfuzz/plugins/encoders/encoders.py
wfuzz/plugins/iterators/__init__.py
wfuzz/plugins/iterators/iterations.py
wfuzz/plugins/payloads/__init__.py
wfuzz/plugins/payloads/autorize.py
wfuzz/plugins/payloads/bing.py
wfuzz/plugins/payloads/buffer_overflow.py
wfuzz/plugins/payloads/burpitem.py
wfuzz/plugins/payloads/burplog.py
wfuzz/plugins/payloads/burpstate.py
wfuzz/plugins/payloads/dirwalk.py
wfuzz/plugins/payloads/file.py
wfuzz/plugins/payloads/guitab.py
wfuzz-3.1.0.dist-info/LICENSE
wfuzz-3.1.0.dist-info/METADATA
wfuzz-3.1.0.dist-info/WHEEL
wfuzz-3.1.0.dist-info/entry_points.txt
wfuzz-3.1.0.dist-info/top_level.txt
wfuzz-3.1.0.dist-info/RECORD
