Metadata-Version: 2.1
Name: wfuzz
Version: 3.1.0
Summary: Wfuzz - The web fuzzer
Home-page: http://wfuzz.org
Author: Xavi Mendez (@x4vi_mendez)
Author-email: xmendez@edge-security.com
License: GPLv2
Platform: UNKNOWN
Classifier: Development Status :: 4 - Beta
Classifier: Natural Language :: English
Classifier: License :: OSI Approved :: GNU General Public License v2 (GPLv2)
Classifier: Programming Language :: Python
Classifier: Programming Language :: Python :: 3
Classifier: Programming Language :: Python :: 3.4
Classifier: Programming Language :: Python :: 3.5
Classifier: Programming Language :: Python :: 3.6
Classifier: Programming Language :: Python :: 3.7
Classifier: Programming Language :: Python :: 3.8
Requires-Python: >=2.6
Provides-Extra: dev
Provides-Extra: docs
